CHANGES.rst
MANIFEST.in
README.txt
setup.py
src/xml_marshaller/__init__.py
src/xml_marshaller/xml_marshaller.py
src/xml_marshaller.egg-info/PKG-INFO
src/xml_marshaller.egg-info/SOURCES.txt
src/xml_marshaller.egg-info/dependency_links.txt
src/xml_marshaller.egg-info/not-zip-safe
src/xml_marshaller.egg-info/requires.txt
src/xml_marshaller.egg-info/top_level.txt
src/xml_marshaller/doc/xml_marshaller.xsd
src/xml_marshaller/tests/__init__.py
src/xml_marshaller/tests/test_xml_marshaller.py