Metadata-Version: 1.1
Name: xml-marshaller
Version: 1.0.1
Summary: Converting Python objects to XML and back again.
Home-page: http://www.python.org/community/sigs/current/xml-sig/
Author: Nicolas Delaby
Author-email: nicolas@nexedi.com
License: Python License (CNRI Python License)
Keywords: XML marshaller
Platform: UNKNOWN
Classifier: Development Status :: 4 - Beta
Classifier: Intended Audience :: Developers
Classifier: License :: OSI Approved :: Python License (CNRI Python License)
Classifier: Operating System :: OS Independent
Classifier: Topic :: Text Processing :: Markup :: XML
